setup.py
buoyantSimpleFlux/__init__.py
buoyantSimpleFlux.egg-info/PKG-INFO
buoyantSimpleFlux.egg-info/SOURCES.txt
buoyantSimpleFlux.egg-info/dependency_links.txt
buoyantSimpleFlux.egg-info/entry_points.txt
buoyantSimpleFlux.egg-info/requires.txt
buoyantSimpleFlux.egg-info/top_level.txt
buoyantSimpleFlux.egg-info/zip-safe
buoyantSimpleFlux/r1_6/__init__.py
buoyantSimpleFlux/r1_6_dev/__init__.py
buoyantSimpleFlux/r1_7_0/__init__.py
buoyantSimpleFlux/r2_0_0/__init__.py
buoyantSimpleFlux/r2_1_0/__init__.py